preemo/__init__.py
preemo/api/__init__.py
preemo/api/default_api.py
preemo/api_client.py
preemo/api_response.py
preemo/configuration.py
preemo/exceptions.py
preemo/models/__init__.py
preemo/models/create_license_error.py
preemo/models/create_model_error.py
preemo/models/create_model_request.py
preemo/models/create_model_request_body.py
preemo/models/create_model_request_body_model.py
preemo/models/create_model_request_model.py
preemo/models/delete_model_error.py
preemo/models/get_license200_response.py
preemo/models/get_license4_xx_response.py
preemo/models/get_license_error.py
preemo/models/get_license_success.py
preemo/models/get_model200_response.py
preemo/models/get_model_error.py
preemo/models/get_model_licenses200_response.py
preemo/models/get_model_licenses_error.py
preemo/models/get_model_licenses_success.py
preemo/models/get_model_success.py
preemo/models/list_models200_response.py
preemo/models/list_models_error.py
preemo/models/list_models_success.py
preemo/models/query_model200_response.py
preemo/models/query_model_error.py
preemo/models/query_model_success.py
preemo/models/train_model_error.py
preemo/models/train_model_raw_error.py
preemo/models/train_model_raw_request_body.py
preemo/models/train_model_raw_request_body_training_arguments.py
preemo/models/train_model_raw_success.py
preemo/models/train_model_request.py
preemo/models/train_model_request_body.py
preemo/models/train_model_request_body_training_arguments.py
preemo/models/train_model_success.py
preemo/py.typed
preemo/rest.py
preemo-1.0.0.dev0.dist-info/METADATA
preemo-1.0.0.dev0.dist-info/WHEEL
preemo-1.0.0.dev0.dist-info/RECORD
